.config
.testr.conf
.vagrantplugins
AUTHORS
ChangeLog
LICENSE
MANIFEST.in
README.rst
Vagrantfile
doc-test.conf
requirements.txt
run_tests.sh
setup.cfg
setup.py
snapshotter.py
test-requirements.txt
tox.ini
vagrant-settings.yaml_defaults
bootstrap/README.md
bootstrap/build-image.yaml
bootstrap/packer.yaml
bootstrap/solar-master.json
bootstrap/http/preseed.cfg
bootstrap/playbooks/build-main.yaml
bootstrap/playbooks/pxe.yaml
bootstrap/playbooks/solar-agent.yaml
bootstrap/playbooks/solar.yaml
bootstrap/playbooks/files/cleanup.sh
bootstrap/playbooks/files/dnsmasq_pxe.conf
bootstrap/playbooks/files/hiera.yaml
bootstrap/playbooks/files/minimize.sh
bootstrap/playbooks/files/nginx.cfg
bootstrap/playbooks/files/nginx_vagrant_dir.cfg
bootstrap/playbooks/files/prov.json
bootstrap/playbooks/files/pxelinux.cfg
bootstrap/playbooks/files/ssh_conf
bootstrap/playbooks/files/sshd.sh
bootstrap/playbooks/files/supervisor.conf
bootstrap/playbooks/files/ubuntu-ansible.sh
bootstrap/playbooks/files/update.sh
bootstrap/playbooks/files/vagrant.sh
bootstrap/playbooks/files/vmtool.sh
bootstrap/playbooks/tasks/base.yaml
bootstrap/playbooks/tasks/cloud_archive.yaml
bootstrap/playbooks/tasks/docker.yaml
bootstrap/playbooks/tasks/mos.yaml
bootstrap/playbooks/tasks/puppet.yaml
bootstrap/playbooks/tasks/ssh_conf.yaml
bootstrap/playbooks/tasks/worker_upstart.yaml
bootstrap/vagrant_plugins/noop.rb
doc/Makefile
doc/commit-log.md
doc/events.md
doc/libvirt.md
doc/removal.md
doc/source/architecture.rst
doc/source/conf.py
doc/source/deployment_plan.rst
doc/source/development.rst
doc/source/examples.rst
doc/source/faq.rst
doc/source/fuel_modular_tasks.rst
doc/source/glossary.rst
doc/source/index.rst
doc/source/installation.rst
doc/source/resource.rst
doc/source/resource_repository.rst
doc/source/transports.rst
doc/source/usage.rst
doc/source/_static/.gitignore
doc/source/_static/solar_internal_architecture.png
doc/source/_templates/.gitignore
doc/source/orchestration/configuration.rst
solar.egg-info/PKG-INFO
solar.egg-info/SOURCES.txt
solar.egg-info/dependency_links.txt
solar.egg-info/entry_points.txt
solar.egg-info/not-zip-safe
solar.egg-info/pbr.json
solar.egg-info/requires.txt
solar.egg-info/top_level.txt
