Metadata-Version: 1.1
Name: solar
Version: 0.2.1
Summary: Deployment tool
Home-page: http://mirantis.com
Author: Mirantis Inc.
Author-email: product@mirantis.com
License: Apache-2
Keywords: deployment
Platform: UNKNOWN
Classifier: Development Status :: 4 - Beta
Classifier: License :: OSI Approved :: Apache Software License
Classifier: Programming Language :: Python
Classifier: Programming Language :: Python :: 2.7
Classifier: Topic :: System :: Software Distribution
